causalif/__init__.py
causalif/core.py
causalif/engine.py
causalif/prompts.py
causalif/tools.py
causalif/visualization.py
causalif-0.1.6.dist-info/licenses/LICENSE
causalif-0.1.6.dist-info/licenses/NOTICE
causalif-0.1.6.dist-info/METADATA
causalif-0.1.6.dist-info/WHEEL
causalif-0.1.6.dist-info/entry_points.txt
causalif-0.1.6.dist-info/top_level.txt
causalif-0.1.6.dist-info/RECORD
