Metadata-Version: 2.4
Name: causalif
Version: 0.1.6
Summary: LLM assisted causal reasoning with JAX and RAG
Home-page: https://github.com/bossubhr/Causalif-private
Author: Subhro Bose
Author-email: bossubhr@amazon.co.uk
Project-URL: Bug Reports, https://github.com/bossubhr/Causalif-private/issues
Project-URL: Source, https://github.com/bossubhr/Causalif-private
Project-URL: Documentation, https://github.com/bossubhr/Causalif-private/blob/feature-Subhro/README.md
Keywords: causal reasoning,machine learning,nlp,rag,jax,networkx,causal inference,genai,llm
Classifier: Development Status :: 3 - Alpha
Classifier: Intended Audience :: Developers
Classifier: Intended Audience :: Science/Research
Classifier: License :: OSI Approved :: Apache Software License
Classifier: Operating System :: OS Independent
Classifier: Programming Language :: Python :: 3
Classifier: Programming Language :: Python :: 3.8
Classifier: Programming Language :: Python :: 3.9
Classifier: Programming Language :: Python :: 3.10
Classifier: Programming Language :: Python :: 3.11
Classifier: Topic :: Scientific/Engineering :: Artificial Intelligence
Classifier: Topic :: Scientific/Engineering :: Information Analysis
Requires-Python: >=3.8
License-File: LICENSE
License-File: NOTICE
Requires-Dist: jax>=0.4.0
Requires-Dist: jaxlib>=0.4.0
Requires-Dist: pandas>=1.3.0
Requires-Dist: networkx>=2.6.0
Requires-Dist: plotly>=5.0.0
Requires-Dist: langchain-core>=0.1.0
Requires-Dist: numpy>=1.21.0
Requires-Dist: scikit-learn>=1.0.0
Requires-Dist: nest-asyncio>=1.5.0
Provides-Extra: dev
Requires-Dist: pytest>=6.0; extra == "dev"
Requires-Dist: pytest-cov>=2.0; extra == "dev"
Requires-Dist: black>=21.0; extra == "dev"
Requires-Dist: flake8>=3.8; extra == "dev"
Requires-Dist: mypy>=0.800; extra == "dev"
Provides-Extra: jupyter
Requires-Dist: nest-asyncio>=1.5.0; extra == "jupyter"
Requires-Dist: jupyter>=1.0.0; extra == "jupyter"
Requires-Dist: ipywidgets>=7.0.0; extra == "jupyter"
Dynamic: author
Dynamic: author-email
Dynamic: classifier
Dynamic: description
Dynamic: description-content-type
Dynamic: home-page
Dynamic: keywords
Dynamic: license-file
Dynamic: project-url
Dynamic: provides-extra
Dynamic: requires-dist
Dynamic: requires-python
Dynamic: summary
